valvebsp/__init__.py
valvebsp/bsp.py
valvebsp/constants.py
valvebsp/exceptions.py
valvebsp/lumps.py
valvebsp/profiles.py
valvebsp/structs/__init__.py
valvebsp/structs/bsp.py
valvebsp/structs/bsp_header.py
valvebsp/structs/common.py
valvebsp/structs/flags.py
valvebsp/structs/lump_0.py
valvebsp/structs/lump_1.py
valvebsp/structs/lump_10.py
valvebsp/structs/lump_11.py
valvebsp/structs/lump_12.py
valvebsp/structs/lump_13.py
valvebsp/structs/lump_14.py
valvebsp/structs/lump_15.py
valvebsp/structs/lump_16.py
valvebsp/structs/lump_17.py
valvebsp/structs/lump_18.py
valvebsp/structs/lump_19.py
valvebsp/structs/lump_2.py
valvebsp/structs/lump_20.py
valvebsp/structs/lump_21.py
valvebsp/structs/lump_22.py
valvebsp/structs/lump_23.py
valvebsp/structs/lump_24.py
valvebsp/structs/lump_25.py
valvebsp/structs/lump_26.py
valvebsp/structs/lump_27.py
valvebsp/structs/lump_28.py
valvebsp/structs/lump_29.py
valvebsp/structs/lump_3.py
valvebsp/structs/lump_30.py
valvebsp/structs/lump_31.py
valvebsp/structs/lump_32.py
valvebsp/structs/lump_33.py
valvebsp/structs/lump_34.py
valvebsp/structs/lump_35.py
valvebsp/structs/lump_36.py
valvebsp/structs/lump_37.py
valvebsp/structs/lump_38.py
valvebsp/structs/lump_39.py
valvebsp/structs/lump_4.py
valvebsp/structs/lump_40.py
valvebsp/structs/lump_41.py
valvebsp/structs/lump_42.py
valvebsp/structs/lump_43.py
valvebsp/structs/lump_44.py
valvebsp/structs/lump_45.py
valvebsp/structs/lump_46.py
valvebsp/structs/lump_47.py
valvebsp/structs/lump_48.py
valvebsp/structs/lump_49.py
valvebsp/structs/lump_5.py
valvebsp/structs/lump_50.py
valvebsp/structs/lump_51.py
valvebsp/structs/lump_52.py
valvebsp/structs/lump_53.py
valvebsp/structs/lump_54.py
valvebsp/structs/lump_55.py
valvebsp/structs/lump_56.py
valvebsp/structs/lump_57.py
valvebsp/structs/lump_58.py
valvebsp/structs/lump_59.py
valvebsp/structs/lump_6.py
valvebsp/structs/lump_60.py
valvebsp/structs/lump_61.py
valvebsp/structs/lump_62.py
valvebsp/structs/lump_63.py
valvebsp/structs/lump_7.py
valvebsp-1.3.14.dist-info/LICENSE
valvebsp-1.3.14.dist-info/METADATA
valvebsp-1.3.14.dist-info/WHEEL
valvebsp-1.3.14.dist-info/top_level.txt
valvebsp-1.3.14.dist-info/RECORD
